cloudmusic/__init__.py
cloudmusic/__version__.py
cloudmusic/api.py
cloudmusic/cloudmusic.py
cloudmusic/download.py
cloudmusic/encrypt.py
cloudmusic/musicObj.py
cloudmusic/query.py
cloudmusic/sessions.py
cloudmusic/test.py
cloudmusic/userObj.py
cloudmusic-0.1.1.dist-info/LICENSE
cloudmusic-0.1.1.dist-info/METADATA
cloudmusic-0.1.1.dist-info/WHEEL
cloudmusic-0.1.1.dist-info/top_level.txt
cloudmusic-0.1.1.dist-info/RECORD
