Metadata-Version: 2.1
Name: cloudmusic
Version: 0.1.1
Summary: 网易云爬虫解决方案
Home-page: https://github.com/p697/cloudmusic
Author: p697
Author-email: 254139147@qq.com
License: MIT
Platform: UNKNOWN
Classifier: License :: OSI Approved :: MIT License
Classifier: Programming Language :: Python
Classifier: Programming Language :: Python :: 3
Classifier: Programming Language :: Python :: 3.6
Classifier: Programming Language :: Python :: Implementation :: CPython
Classifier: Programming Language :: Python :: Implementation :: PyPy
Requires-Python: >=3.0.0
Requires-Dist: requests
Requires-Dist: lxml
Requires-Dist: pycryptodomex
Requires-Dist: threadpool
